async_zulip_bot_sdk-1.2.0.dist-info/licenses/LICENSE
async_zulip_bot_sdk-1.2.0.dist-info/licenses/NOTICE
bot_sdk/__init__.py
bot_sdk/async_zulip.py
bot_sdk/bot.py
bot_sdk/cli.py
bot_sdk/commands.py
bot_sdk/config.py
bot_sdk/console.py
bot_sdk/i18n.py
bot_sdk/loader.py
bot_sdk/logging.py
bot_sdk/permissions.py
bot_sdk/runner.py
bot_sdk/storage.py
bot_sdk/db/__init__.py
bot_sdk/db/cli.py
bot_sdk/db/database.py
bot_sdk/db/repository.py
bot_sdk/models/__init__.py
bot_sdk/models/api/__init__.py
bot_sdk/models/api/request.py
bot_sdk/models/api/response.py
bot_sdk/models/api/types.py
bot_sdk/models/data/__init__.py
async_zulip_bot_sdk-1.2.0.dist-info/METADATA
async_zulip_bot_sdk-1.2.0.dist-info/WHEEL
async_zulip_bot_sdk-1.2.0.dist-info/entry_points.txt
async_zulip_bot_sdk-1.2.0.dist-info/top_level.txt
async_zulip_bot_sdk-1.2.0.dist-info/RECORD
