Metadata-Version: 2.4
Name: async-zulip-bot-sdk
Version: 1.2.0
Summary: Add your description here
Home-page: 
Author: Stewitch
Author-email: sunksugar24@gmail.com
Requires-Python: >=3.12
License-File: LICENSE
License-File: NOTICE
Requires-Dist: aiosqlite>=0.20.0
Requires-Dist: alembic>=1.13.0
Requires-Dist: distro>=1.9.0
Requires-Dist: httpx>=0.28.1
Requires-Dist: loguru>=0.7.3
Requires-Dist: pydantic>=2.12.5
Requires-Dist: sqlalchemy>=2.0.0
Requires-Dist: ruamel-yaml>=0.19.1
Requires-Dist: rich>=14.2.0
Requires-Dist: prompt-toolkit>=3.0.52
Dynamic: author
Dynamic: author-email
Dynamic: license-file
Dynamic: requires-python
